multiplug/__init__.py
multiplug/bash_mod.py
multiplug/error.py
multiplug/importer.py
multiplug/nim_mod.py
multiplug/plugin_api.py
multiplug/plugins.py
multiplug/py_mod.py
multiplug/rust_mod.py
multiplug-1.2.dist-info/LICENSE.txt
multiplug-1.2.dist-info/METADATA
multiplug-1.2.dist-info/WHEEL
multiplug-1.2.dist-info/top_level.txt
multiplug-1.2.dist-info/RECORD
