Metadata-Version: 2.1
Name: multiplug
Version: 1.2
Summary: Plugin system supporting multiple programming languages
Home-page: https://github.com/ggonnella/multiplug
Author: Giorgio Gonnella
Author-email: gonnella@zbh.uni-hamburg.de
License: ISC
Keywords: plugins,extensions,nim,rust,shell,bash
Classifier: Development Status :: 5 - Production/Stable
Classifier: Environment :: Console
Classifier: Intended Audience :: Developers
Classifier: Intended Audience :: End Users/Desktop
Classifier: Intended Audience :: Science/Research
Classifier: License :: OSI Approved :: ISC License (ISCL)
Classifier: Operating System :: MacOS :: MacOS X
Classifier: Operating System :: POSIX :: Linux
Classifier: Programming Language :: Python :: 3 :: Only
Classifier: Topic :: Software Development :: Libraries
License-File: LICENSE.txt
Requires-Dist: sh
Requires-Dist: nimporter (==1.1.0)
Requires-Dist: schema
Requires-Dist: docopt
Requires-Dist: maturin (==0.12.11)
